openhab/__init__.py
openhab/crud.py
python_openhab_crud-1.0.0.dist-info/LICENSE
python_openhab_crud-1.0.0.dist-info/METADATA
python_openhab_crud-1.0.0.dist-info/WHEEL
python_openhab_crud-1.0.0.dist-info/top_level.txt
python_openhab_crud-1.0.0.dist-info/RECORD
