Metadata-Version: 2.1
Name: python-openhab-crud
Version: 1.0.0
Summary: A simple CRUD for accessing the openHAB REST API. Whether via the cloud or locally.
Home-page: https://github.com/Michdo93/python-openhab-crud
Download-URL: https://github.com/Michdo93/python-openhab-crud
Author: Michael Dörflinger
Author-email: michaeldoerflinger93@gmail.com
License: MIT License
Project-URL: Bug Tracker, https://github.com/Michdo93/python-openhab-crud/issues
Project-URL: Documentation, https://github.com/Michdo93/python-openhab-crud/blob/main/README.md
Project-URL: Source Code, https://github.com/Michdo93/python-openhab-crud
Keywords: openHAB
Classifier: Development Status :: 4 - Beta
Classifier: License :: OSI Approved :: MIT License
Classifier: Intended Audience :: Developers
Classifier: Operating System :: OS Independent
Classifier: Programming Language :: Python :: 3
Classifier: Programming Language :: Python :: 3 :: Only
Requires-Python: >=3.5
License-File: LICENSE
Requires-Dist: requests (>=2.28.1)
